ksfctl/__init__.py
ksfctl/cmd/__init__.py
ksfctl/cmd/cmd.py
ksfctl/cmd/options.py
ksfctl/generate/__init__.py
ksfctl/generate/cpp/__init__.py
ksfctl/generate/cpp/generator.py
ksfctl/generate/cpp/parser.py
ksfctl/generate/cpp/template.py
ksfctl/generate/ksf/__init__.py
ksfctl/generate/ksf/generator.py
ksfctl/generate/ksf/parser.py
ksfctl/parser/__init__.py
ksfctl/parser/ksf.py
ksfctl/parser/parser.py
ksfctl/parser/token.py
ksfctl/parser/tools.py
ksfctl-0.2.4.dist-info/LICENSE
ksfctl-0.2.4.dist-info/METADATA
ksfctl-0.2.4.dist-info/WHEEL
ksfctl-0.2.4.dist-info/entry_points.txt
ksfctl-0.2.4.dist-info/top_level.txt
ksfctl-0.2.4.dist-info/RECORD
