Metadata-Version: 2.1
Name: ksfctl
Version: 0.2.4
Summary: a auto generator tools for ksf protocol files, and some useful tools
Keywords: ksf,client,generator,tool
License-File: LICENSE
Requires-Dist: Click (>=8.0.0)
Requires-Dist: ply (>=3.0.0)
Requires-Dist: pyyaml (>=5.4.1)
